heartpole/__init__.py
heartpole-1.2.dist-info/LICENSE
heartpole-1.2.dist-info/METADATA
heartpole-1.2.dist-info/WHEEL
heartpole-1.2.dist-info/RECORD
