Metadata-Version: 2.1
Name: heartpole
Version: 1.2
Summary: A simple Healthcare-themed Gymnasium for benchmarking Reinforcement Learning algorithms
License: MIT
Author: Vadim Liventsev
Author-email: dev@vadim.me
Requires-Python: >=3.11,<4.0
Classifier: License :: OSI Approved :: MIT License
Classifier: Programming Language :: Python :: 3
Classifier: Programming Language :: Python :: 3.11
Classifier: Programming Language :: Python :: 3.12
Requires-Dist: gymnasium (>=0.29,<0.30)
Requires-Dist: numpy (>=1.24,<2.0)
